octoprint_nanny/__init__.py
octoprint_nanny/env.py
octoprint_nanny/error.py
octoprint_nanny/events.py
octoprint_nanny/exceptions.py
octoprint_nanny/executor.py
octoprint_nanny/plugins.py
octoprint_nanny/worker.py
octoprint_nanny/clients/__init__.py
octoprint_nanny/clients/rest.py
octoprint_nanny/static/css/printnanny.css
octoprint_nanny/static/img/ignore_mask_example.gif
octoprint_nanny/static/img/logo-square-excited.png
octoprint_nanny/static/img/print_nanny_logo.png
octoprint_nanny/static/img/sleeping.png
octoprint_nanny/static/img/wizard_example.jpg
octoprint_nanny/static/js/octo_printnanny.js
octoprint_nanny/static/less/nanny.less
octoprint_nanny/static/vendor/janus/janus.js
octoprint_nanny/static/vendor/janus/webrtc-adaptor.js
octoprint_nanny/templates/README.txt
octoprint_nanny/templates/octoprint_nanny_navbar.jinja2
octoprint_nanny/templates/octoprint_nanny_settings.jinja2
octoprint_nanny/templates/octoprint_nanny_settings_shared.jinja2
octoprint_nanny/templates/octoprint_nanny_unsupported_os.jinja2
octoprint_nanny/templates/octoprint_nanny_wizard.jinja2
octoprint_nanny/templates/snippets/januswebcam_janusApiToken.jinja2
octoprint_nanny/templates/snippets/januswebcam_janusApiUrl.jinja2
octoprint_nanny/templates/snippets/januswebcam_streamControl.jinja2
octoprint_nanny/templates/snippets/januswebcam_streamWebrtcIceServers.jinja2
octoprint_nanny/utils/__init__.py
octoprint_nanny/utils/dict_merge.py
octoprint_nanny/utils/encoder.py
octoprint_nanny/utils/logger.py
octoprint_nanny/utils/printnanny_os.py
octoprint_nanny/vendor/__init__.py
octoprint_nanny/vendor/octoprint_setuptools/__init__.py
OctoPrint_Nanny-0.16.0.dist-info/LICENSE
OctoPrint_Nanny-0.16.0.dist-info/METADATA
OctoPrint_Nanny-0.16.0.dist-info/WHEEL
OctoPrint_Nanny-0.16.0.dist-info/entry_points.txt
OctoPrint_Nanny-0.16.0.dist-info/top_level.txt
OctoPrint_Nanny-0.16.0.dist-info/RECORD
